Metadata-Version: 2.1
Name: pepg-es
Version: 0.0.5
Summary: Python Implementation of Parameter-exploring Policy Gradients Evolution Strategy
Home-page: https://github.com/goktug97/PEPG-ES
Author: Göktuğ Karakaşlı
Author-email: karakasligk@gmail.com
License: MIT
Download-URL: https://github.com/goktug97/PEPG-ES/archive/v0.0.5.tar.gz
Platform: UNKNOWN
Classifier: Programming Language :: Python :: 3
Classifier: License :: OSI Approved :: MIT License
Classifier: Operating System :: POSIX :: Linux
Requires-Python: >=3.6
